{"name":"Webrammeverk-express","tagline":"Express intro-workshop","body":"# Følg disse stegene for å sette opp et prosjekt klart for worshop-en om Express:\r\n\r\n1. Installer [node](http://nodejs.org/download/).\r\n2. Installer yeoman?\r\n\r\n## Følg disse stegene for å sette opp et prosjekt klart for worshop-en om Express:\r\n\r\n1. Installer [node](http://nodejs.org/download/).\r\n2. Installer yeoman?\r\n\r\n### Følg disse stegene for å sette opp et prosjekt klart for worshop-en om Express:\r\n\r\n1. Installer [node](http://nodejs.org/download/).\r\n2. Installer yeoman?\r\n\r\nFølg disse stegene for å sette opp et prosjekt klart for worshop-en om Express:\r\n\r\n1. Installer [node](http://nodejs.org/download/).\r\n2. Installer yeoman?\r\n\r\nFølg disse stegene for å sette opp et prosjekt klart for worshop-en om Express:\r\n\r\n1. Installer [node](http://nodejs.org/download/).\r\n2. Installer yeoman?\r\n\r\nFølg disse stegene for å sette opp et prosjekt klart for worshop-en om Express:\r\n\r\n1. Installer [node](http://nodejs.org/download/).\r\n2. Installer yeoman?\r\n\r\nFølg disse stegene for å sette opp et prosjekt klart for worshop-en om Express:\r\n\r\n1. Installer [node](http://nodejs.org/download/).\r\n2. Installer yeoman?\r\n\r\nFølg disse stegene for å sette opp et prosjekt klart for worshop-en om Express:\r\n\r\n1. Installer [node](http://nodejs.org/download/).\r\n2. Installer yeoman?\r\n\r\nFølg disse stegene for å sette opp et prosjekt klart for worshop-en om Express:\r\n\r\n1. Installer [node](http://nodejs.org/download/).\r\n2. Installer yeoman?\r\n\r\n","google":"","note":"Don't delete this file! It's used internally to help with page regeneration."}